{
  "todos": [
    {
      "id": "097a",
      "createdAt": "2024-02-29T13:19:27.110Z",
      "lastModifiedAt": "2024-02-29T15:30:27.904Z",
      "status": "todo",
      "description": "asdsadsad1"
    },
    {
      "id": "2e42",
      "description": "asdasds",
      "createdAt": "2024-02-29T13:19:29.545Z",
      "lastModifiedAt": "2024-02-29T15:30:04.417Z",
      "status": "todo"
    },
    {
      "id": "9725",
      "createdAt": "2024-02-29T15:28:18.461Z",
      "lastModifiedAt": "2024-02-29T15:28:18.461Z",
      "status": "todo",
      "description": "2"
    }
  ]
}